faf/__init__.py
faf/_version.py
faf/cli.py
faf/datadog.py
faf/relayer.py
faf/tests/__init__.py
faf/tests/test_datadog.py
faf/tests/test_relayer.py
faf-0.5.2.dist-info/DESCRIPTION.rst
faf-0.5.2.dist-info/entry_points.txt
faf-0.5.2.dist-info/METADATA
faf-0.5.2.dist-info/metadata.json
faf-0.5.2.dist-info/pbr.json
faf-0.5.2.dist-info/RECORD
faf-0.5.2.dist-info/top_level.txt
faf-0.5.2.dist-info/WHEEL
